<root>
  <plate>zoo</plate>
  <every>894785129.1519098</every>
  <to>
    <church>1499934632.6463704</church>
    <along>-1503535372.1836905</along>
    <surface>1257511142.7794971</surface>
    <golden>
      <body>brain</body>
      <potatoes>-931076515.3095288</potatoes>
      <contrast>fear</contrast>
      <shallow>-1687739721.8787646</shallow>
      <faster>it</faster>
      <visitor>661860075</visitor>
    </golden>
    <upper>
      <eager>drawn</eager>
      <toward>-838798072.4823685</toward>
      <differ>-1560007650</differ>
      <frozen>recent</frozen>
      <fog>1176422055.264957</fog>
      <eventually>ranch</eventually>
    </upper>
    <national>hand</national>
  </to>
  <rocky>1009957856</rocky>
  <center>maybe</center>
  <local>-1142268255.0697827</local>
</root>
